{
  "checksum": "2bffe458dd97b7842e716bc5ade938ff",
  "root": "reason-language-server@link-dev:./package.json",
  "node": {
    "rex-json@1.4.0@d41d8cd9": {
      "id": "rex-json@1.4.0@d41d8cd9",
      "name": "rex-json",
      "version": "1.4.0",
      "source": {
        "type": "install",
        "source": [
          "archive:https://registry.npmjs.org/rex-json/-/rex-json-1.4.0.tgz#sha1:d93796d0a33920ca977a177aec5628950ebeb04a"
        ]
      },
      "overrides": [],
      "dependencies": [],
      "devDependencies": []
    },
    "reason-language-server@link-dev:./package.json": {
      "id": "reason-language-server@link-dev:./package.json",
      "name": "reason-language-server",
      "version": "link-dev:./package.json",
      "source": {
        "type": "link-dev",
        "path": ".",
        "manifest": "package.json"
      },
      "overrides": [],
      "dependencies": [
        "rex-json@1.4.0@d41d8cd9", "ocaml@4.7.1004@d41d8cd9",
        "@opam/ppxlib@opam:0.9.0@bfabe269",
        "@opam/ppx_tools_versioned@opam:5.2.3@4994ec80",
        "@opam/ppx_tools@opam:5.1+4.06.0@a9357225",
        "@opam/ppx_deriving@opam:4.4@43678d5a",
        "@opam/ocaml-migrate-parsetree@opam:1.4.0@7f2e4334",
        "@opam/dune@opam:1.11.3@9894df55", "@esy-ocaml/reason@3.5.0@d41d8cd9"
      ],
      "devDependencies": []
    },
    "ocaml@4.7.1004@d41d8cd9": {
      "id": "ocaml@4.7.1004@d41d8cd9",
      "name": "ocaml",
      "version": "4.7.1004",
      "source": {
        "type": "install",
        "source": [
          "archive:https://registry.npmjs.org/ocaml/-/ocaml-4.7.1004.tgz#sha1:731ca0ddb4d845d2ed2da8af50f70c5ba9092114"
        ]
      },
      "overrides": [],
      "dependencies": [],
      "devDependencies": []
    },
    "@opam/stdio@opam:v0.12.0@04b3b004": {
      "id": "@opam/stdio@opam:v0.12.0@04b3b004",
      "name": "@opam/stdio",
      "version": "opam:v0.12.0",
      "source": {
        "type": "install",
        "source": [
          "archive:https://opam.ocaml.org/cache/md5/b2/b261ff2d5667fde960c95e50cff668da#md5:b261ff2d5667fde960c95e50cff668da",
          "archive:https://ocaml.janestreet.com/ocaml-core/v0.12/files/stdio-v0.12.0.tar.gz#md5:b261ff2d5667fde960c95e50cff668da"
        ],
        "opam": {
          "name": "stdio",
          "version": "v0.12.0",
          "path": "esy.lock/opam/stdio.v0.12.0"
        }
      },
      "overrides": [],
      "dependencies": [
        "ocaml@4.7.1004@d41d8cd9", "@opam/dune@opam:1.11.3@9894df55",
        "@opam/base@opam:v0.12.2@4eee02b5",
        "@esy-ocaml/substs@0.0.1@d41d8cd9"
      ],
      "devDependencies": [
        "ocaml@4.7.1004@d41d8cd9", "@opam/dune@opam:1.11.3@9894df55",
        "@opam/base@opam:v0.12.2@4eee02b5"
      ]
    },
    "@opam/sexplib0@opam:v0.12.0@e432406d": {
      "id": "@opam/sexplib0@opam:v0.12.0@e432406d",
      "name": "@opam/sexplib0",
      "version": "opam:v0.12.0",
      "source": {
        "type": "install",
        "source": [
          "archive:https://opam.ocaml.org/cache/md5/24/2486a25d3a94da9a94acc018b5f09061#md5:2486a25d3a94da9a94acc018b5f09061",
          "archive:https://ocaml.janestreet.com/ocaml-core/v0.12/files/sexplib0-v0.12.0.tar.gz#md5:2486a25d3a94da9a94acc018b5f09061"
        ],
        "opam": {
          "name": "sexplib0",
          "version": "v0.12.0",
          "path": "esy.lock/opam/sexplib0.v0.12.0"
        }
      },
      "overrides": [],
      "dependencies": [
        "ocaml@4.7.1004@d41d8cd9", "@opam/dune@opam:1.11.3@9894df55",
        "@esy-ocaml/substs@0.0.1@d41d8cd9"
      ],
      "devDependencies": [
        "ocaml@4.7.1004@d41d8cd9", "@opam/dune@opam:1.11.3@9894df55"
      ]
    },
    "@opam/result@opam:1.4@6fb665c3": {
      "id": "@opam/result@opam:1.4@6fb665c3",
      "name": "@opam/result",
      "version": "opam:1.4",
      "source": {
        "type": "install",
        "source": [
          "archive:https://opam.ocaml.org/cache/md5/d3/d3162dbc501a2af65c8c71e0866541da#md5:d3162dbc501a2af65c8c71e0866541da",
          "archive:https://github.com/janestreet/result/archive/1.4.tar.gz#md5:d3162dbc501a2af65c8c71e0866541da"
        ],
        "opam": {
          "name": "result",
          "version": "1.4",
          "path": "esy.lock/opam/result.1.4"
        }
      },
      "overrides": [],
      "dependencies": [
        "ocaml@4.7.1004@d41d8cd9", "@opam/dune@opam:1.11.3@9894df55",
        "@esy-ocaml/substs@0.0.1@d41d8cd9"
      ],
      "devDependencies": [
        "ocaml@4.7.1004@d41d8cd9", "@opam/dune@opam:1.11.3@9894df55"
      ]
    },
    "@opam/ppxlib@opam:0.9.0@bfabe269": {
      "id": "@opam/ppxlib@opam:0.9.0@bfabe269",
      "name": "@opam/ppxlib",
      "version": "opam:0.9.0",
      "source": {
        "type": "install",
        "source": [
          "archive:https://opam.ocaml.org/cache/sha256/d2/d269f882a31ff75095a80793082f7481884ca75ef867c8c409f26ad36f9a0a54#sha256:d269f882a31ff75095a80793082f7481884ca75ef867c8c409f26ad36f9a0a54",
          "archive:https://github.com/ocaml-ppx/ppxlib/archive/0.9.0.tar.gz#sha256:d269f882a31ff75095a80793082f7481884ca75ef867c8c409f26ad36f9a0a54"
        ],
        "opam": {
          "name": "ppxlib",
          "version": "0.9.0",
          "path": "esy.lock/opam/ppxlib.0.9.0"
        }
      },
      "overrides": [],
      "dependencies": [
        "ocaml@4.7.1004@d41d8cd9", "@opam/stdio@opam:v0.12.0@04b3b004",
        "@opam/ppx_derivers@opam:1.2.1@aee9c3db",
        "@opam/ocaml-migrate-parsetree@opam:1.4.0@7f2e4334",
        "@opam/ocaml-compiler-libs@opam:v0.12.0@692d9405",
        "@opam/dune@opam:1.11.3@9894df55",
        "@opam/base@opam:v0.12.2@4eee02b5",
        "@esy-ocaml/substs@0.0.1@d41d8cd9"
      ],
      "devDependencies": [
        "ocaml@4.7.1004@d41d8cd9", "@opam/stdio@opam:v0.12.0@04b3b004",
        "@opam/ppx_derivers@opam:1.2.1@aee9c3db",
        "@opam/ocaml-migrate-parsetree@opam:1.4.0@7f2e4334",
        "@opam/ocaml-compiler-libs@opam:v0.12.0@692d9405",
        "@opam/dune@opam:1.11.3@9894df55", "@opam/base@opam:v0.12.2@4eee02b5"
      ]
    },
    "@opam/ppxfind@opam:1.3@9b29babb": {
      "id": "@opam/ppxfind@opam:1.3@9b29babb",
      "name": "@opam/ppxfind",
      "version": "opam:1.3",
      "source": {
        "type": "install",
        "source": [
          "archive:https://opam.ocaml.org/cache/sha256/d4/d49db026d0e74212c4b475b4e628aa57508c7452a0682d8c96e80c130ab892e4#sha256:d49db026d0e74212c4b475b4e628aa57508c7452a0682d8c96e80c130ab892e4",
          "archive:https://github.com/diml/ppxfind/releases/download/1.3/ppxfind-1.3.tbz#sha256:d49db026d0e74212c4b475b4e628aa57508c7452a0682d8c96e80c130ab892e4"
        ],
        "opam": {
          "name": "ppxfind",
          "version": "1.3",
          "path": "esy.lock/opam/ppxfind.1.3"
        }
      },
      "overrides": [],
      "dependencies": [
        "ocaml@4.7.1004@d41d8cd9", "@opam/ocamlfind@opam:1.8.1@c65fe06a",
        "@opam/ocaml-migrate-parsetree@opam:1.4.0@7f2e4334",
        "@opam/dune@opam:1.11.3@9894df55", "@esy-ocaml/substs@0.0.1@d41d8cd9"
      ],
      "devDependencies": [
        "ocaml@4.7.1004@d41d8cd9", "@opam/ocamlfind@opam:1.8.1@c65fe06a",
        "@opam/ocaml-migrate-parsetree@opam:1.4.0@7f2e4334",
        "@opam/dune@opam:1.11.3@9894df55"
      ]
    },
    "@opam/ppx_tools_versioned@opam:5.2.3@4994ec80": {
      "id": "@opam/ppx_tools_versioned@opam:5.2.3@4994ec80",
      "name": "@opam/ppx_tools_versioned",
      "version": "opam:5.2.3",
      "source": {
        "type": "install",
        "source": [
          "archive:https://opam.ocaml.org/cache/md5/b1/b1455e5a4a1bcd9ddbfcf712ccbd4262#md5:b1455e5a4a1bcd9ddbfcf712ccbd4262",
          "archive:https://github.com/ocaml-ppx/ppx_tools_versioned/archive/5.2.3.tar.gz#md5:b1455e5a4a1bcd9ddbfcf712ccbd4262"
        ],
        "opam": {
          "name": "ppx_tools_versioned",
          "version": "5.2.3",
          "path": "esy.lock/opam/ppx_tools_versioned.5.2.3"
        }
      },
      "overrides": [],
      "dependencies": [
        "ocaml@4.7.1004@d41d8cd9",
        "@opam/ocaml-migrate-parsetree@opam:1.4.0@7f2e4334",
        "@opam/dune@opam:1.11.3@9894df55", "@esy-ocaml/substs@0.0.1@d41d8cd9"
      ],
      "devDependencies": [
        "ocaml@4.7.1004@d41d8cd9",
        "@opam/ocaml-migrate-parsetree@opam:1.4.0@7f2e4334",
        "@opam/dune@opam:1.11.3@9894df55"
      ]
    },
    "@opam/ppx_tools@opam:5.1+4.06.0@a9357225": {
      "id": "@opam/ppx_tools@opam:5.1+4.06.0@a9357225",
      "name": "@opam/ppx_tools",
      "version": "opam:5.1+4.06.0",
      "source": {
        "type": "install",
        "source": [
          "archive:https://opam.ocaml.org/cache/md5/6b/6ba2e9690b1f579ba562b86022d1c308#md5:6ba2e9690b1f579ba562b86022d1c308",
          "archive:https://github.com/ocaml-ppx/ppx_tools/archive/5.1+4.06.0.tar.gz#md5:6ba2e9690b1f579ba562b86022d1c308"
        ],
        "opam": {
          "name": "ppx_tools",
          "version": "5.1+4.06.0",
          "path": "esy.lock/opam/ppx_tools.5.1+4.06.0"
        }
      },
      "overrides": [],
      "dependencies": [
        "ocaml@4.7.1004@d41d8cd9", "@opam/ocamlfind@opam:1.8.1@c65fe06a",
        "@esy-ocaml/substs@0.0.1@d41d8cd9"
      ],
      "devDependencies": [
        "ocaml@4.7.1004@d41d8cd9", "@opam/ocamlfind@opam:1.8.1@c65fe06a"
      ]
    },
    "@opam/ppx_deriving@opam:4.4@43678d5a": {
      "id": "@opam/ppx_deriving@opam:4.4@43678d5a",
      "name": "@opam/ppx_deriving",
      "version": "opam:4.4",
      "source": {
        "type": "install",
        "source": [
          "archive:https://opam.ocaml.org/cache/sha256/c2/c2d85af4cb65a1f163f624590fb0395a164bbfd0d05082092526b669e66bcc34#sha256:c2d85af4cb65a1f163f624590fb0395a164bbfd0d05082092526b669e66bcc34",
          "archive:https://github.com/ocaml-ppx/ppx_deriving/archive/v4.4.tar.gz#sha256:c2d85af4cb65a1f163f624590fb0395a164bbfd0d05082092526b669e66bcc34"
        ],
        "opam": {
          "name": "ppx_deriving",
          "version": "4.4",
          "path": "esy.lock/opam/ppx_deriving.4.4"
        }
      },
      "overrides": [],
      "dependencies": [
        "ocaml@4.7.1004@d41d8cd9", "@opam/result@opam:1.4@6fb665c3",
        "@opam/ppxfind@opam:1.3@9b29babb",
        "@opam/ppx_tools@opam:5.1+4.06.0@a9357225",
        "@opam/ppx_derivers@opam:1.2.1@aee9c3db",
        "@opam/ocaml-migrate-parsetree@opam:1.4.0@7f2e4334",
        "@opam/dune@opam:1.11.3@9894df55", "@opam/cppo@opam:1.6.6@f4f83858",
        "@esy-ocaml/substs@0.0.1@d41d8cd9"
      ],
      "devDependencies": [
        "ocaml@4.7.1004@d41d8cd9", "@opam/result@opam:1.4@6fb665c3",
        "@opam/ppx_tools@opam:5.1+4.06.0@a9357225",
        "@opam/ppx_derivers@opam:1.2.1@aee9c3db",
        "@opam/ocaml-migrate-parsetree@opam:1.4.0@7f2e4334",
        "@opam/dune@opam:1.11.3@9894df55"
      ]
    },
    "@opam/ppx_derivers@opam:1.2.1@aee9c3db": {
      "id": "@opam/ppx_derivers@opam:1.2.1@aee9c3db",
      "name": "@opam/ppx_derivers",
      "version": "opam:1.2.1",
      "source": {
        "type": "install",
        "source": [
          "archive:https://opam.ocaml.org/cache/md5/5d/5dc2bf130c1db3c731fe0fffc5648b41#md5:5dc2bf130c1db3c731fe0fffc5648b41",
          "archive:https://github.com/ocaml-ppx/ppx_derivers/archive/1.2.1.tar.gz#md5:5dc2bf130c1db3c731fe0fffc5648b41"
        ],
        "opam": {
          "name": "ppx_derivers",
          "version": "1.2.1",
          "path": "esy.lock/opam/ppx_derivers.1.2.1"
        }
      },
      "overrides": [],
      "dependencies": [
        "ocaml@4.7.1004@d41d8cd9", "@opam/dune@opam:1.11.3@9894df55",
        "@esy-ocaml/substs@0.0.1@d41d8cd9"
      ],
      "devDependencies": [
        "ocaml@4.7.1004@d41d8cd9", "@opam/dune@opam:1.11.3@9894df55"
      ]
    },
    "@opam/ocamlfind@opam:1.8.1@c65fe06a": {
      "id": "@opam/ocamlfind@opam:1.8.1@c65fe06a",
      "name": "@opam/ocamlfind",
      "version": "opam:1.8.1",
      "source": {
        "type": "install",
        "source": [
          "archive:https://opam.ocaml.org/cache/md5/18/18ca650982c15536616dea0e422cbd8c#md5:18ca650982c15536616dea0e422cbd8c",
          "archive:http://download2.camlcity.org/download/findlib-1.8.1.tar.gz#md5:18ca650982c15536616dea0e422cbd8c",
          "archive:http://download.camlcity.org/download/findlib-1.8.1.tar.gz#md5:18ca650982c15536616dea0e422cbd8c"
        ],
        "opam": {
          "name": "ocamlfind",
          "version": "1.8.1",
          "path": "esy.lock/opam/ocamlfind.1.8.1"
        }
      },
      "overrides": [
        {
          "opamoverride":
            "esy.lock/overrides/opam__s__ocamlfind_opam__c__1.8.1_opam_override"
        }
      ],
      "dependencies": [
        "ocaml@4.7.1004@d41d8cd9", "@opam/conf-m4@opam:1@da6f4f44",
        "@esy-ocaml/substs@0.0.1@d41d8cd9"
      ],
      "devDependencies": [ "ocaml@4.7.1004@d41d8cd9" ]
    },
    "@opam/ocamlbuild@opam:0.14.0@427a2331": {
      "id": "@opam/ocamlbuild@opam:0.14.0@427a2331",
      "name": "@opam/ocamlbuild",
      "version": "opam:0.14.0",
      "source": {
        "type": "install",
        "source": [
          "archive:https://opam.ocaml.org/cache/sha256/87/87b29ce96958096c0a1a8eeafeb6268077b2d11e1bf2b3de0f5ebc9cf8d42e78#sha256:87b29ce96958096c0a1a8eeafeb6268077b2d11e1bf2b3de0f5ebc9cf8d42e78",
          "archive:https://github.com/ocaml/ocamlbuild/archive/0.14.0.tar.gz#sha256:87b29ce96958096c0a1a8eeafeb6268077b2d11e1bf2b3de0f5ebc9cf8d42e78"
        ],
        "opam": {
          "name": "ocamlbuild",
          "version": "0.14.0",
          "path": "esy.lock/opam/ocamlbuild.0.14.0"
        }
      },
      "overrides": [
        {
          "opamoverride":
            "esy.lock/overrides/opam__s__ocamlbuild_opam__c__0.14.0_opam_override"
        }
      ],
      "dependencies": [
        "ocaml@4.7.1004@d41d8cd9", "@esy-ocaml/substs@0.0.1@d41d8cd9"
      ],
      "devDependencies": [ "ocaml@4.7.1004@d41d8cd9" ]
    },
    "@opam/ocaml-migrate-parsetree@opam:1.4.0@7f2e4334": {
      "id": "@opam/ocaml-migrate-parsetree@opam:1.4.0@7f2e4334",
      "name": "@opam/ocaml-migrate-parsetree",
      "version": "opam:1.4.0",
      "source": {
        "type": "install",
        "source": [
          "archive:https://opam.ocaml.org/cache/sha256/23/231fbdc205187b3ee266b535d9cfe44b599067b2f6e97883c782ea7bb577d3b8#sha256:231fbdc205187b3ee266b535d9cfe44b599067b2f6e97883c782ea7bb577d3b8",
          "archive:https://github.com/ocaml-ppx/ocaml-migrate-parsetree/releases/download/v1.4.0/ocaml-migrate-parsetree-v1.4.0.tbz#sha256:231fbdc205187b3ee266b535d9cfe44b599067b2f6e97883c782ea7bb577d3b8"
        ],
        "opam": {
          "name": "ocaml-migrate-parsetree",
          "version": "1.4.0",
          "path": "esy.lock/opam/ocaml-migrate-parsetree.1.4.0"
        }
      },
      "overrides": [],
      "dependencies": [
        "ocaml@4.7.1004@d41d8cd9", "@opam/result@opam:1.4@6fb665c3",
        "@opam/ppx_derivers@opam:1.2.1@aee9c3db",
        "@opam/dune@opam:1.11.3@9894df55", "@esy-ocaml/substs@0.0.1@d41d8cd9"
      ],
      "devDependencies": [
        "ocaml@4.7.1004@d41d8cd9", "@opam/result@opam:1.4@6fb665c3",
        "@opam/ppx_derivers@opam:1.2.1@aee9c3db",
        "@opam/dune@opam:1.11.3@9894df55"
      ]
    },
    "@opam/ocaml-compiler-libs@opam:v0.12.0@692d9405": {
      "id": "@opam/ocaml-compiler-libs@opam:v0.12.0@692d9405",
      "name": "@opam/ocaml-compiler-libs",
      "version": "opam:v0.12.0",
      "source": {
        "type": "install",
        "source": [
          "archive:https://opam.ocaml.org/cache/md5/33/3351925ed99be59829641d2044fc80c0#md5:3351925ed99be59829641d2044fc80c0",
          "archive:https://github.com/janestreet/ocaml-compiler-libs/archive/v0.12.0.tar.gz#md5:3351925ed99be59829641d2044fc80c0"
        ],
        "opam": {
          "name": "ocaml-compiler-libs",
          "version": "v0.12.0",
          "path": "esy.lock/opam/ocaml-compiler-libs.v0.12.0"
        }
      },
      "overrides": [],
      "dependencies": [
        "ocaml@4.7.1004@d41d8cd9", "@opam/dune@opam:1.11.3@9894df55",
        "@esy-ocaml/substs@0.0.1@d41d8cd9"
      ],
      "devDependencies": [
        "ocaml@4.7.1004@d41d8cd9", "@opam/dune@opam:1.11.3@9894df55"
      ]
    },
    "@opam/merlin-extend@opam:0.5@a5dd7d4b": {
      "id": "@opam/merlin-extend@opam:0.5@a5dd7d4b",
      "name": "@opam/merlin-extend",
      "version": "opam:0.5",
      "source": {
        "type": "install",
        "source": [
          "archive:https://opam.ocaml.org/cache/sha256/ca/ca3a38c360c7d4827eb4789abf7a6aa4b6e3b4e3c3ef69a5be64dce4601ec227#sha256:ca3a38c360c7d4827eb4789abf7a6aa4b6e3b4e3c3ef69a5be64dce4601ec227",
          "archive:https://github.com/let-def/merlin-extend/releases/download/v0.5/merlin-extend-v0.5.tbz#sha256:ca3a38c360c7d4827eb4789abf7a6aa4b6e3b4e3c3ef69a5be64dce4601ec227"
        ],
        "opam": {
          "name": "merlin-extend",
          "version": "0.5",
          "path": "esy.lock/opam/merlin-extend.0.5"
        }
      },
      "overrides": [],
      "dependencies": [
        "ocaml@4.7.1004@d41d8cd9", "@opam/dune@opam:1.11.3@9894df55",
        "@opam/cppo@opam:1.6.6@f4f83858", "@esy-ocaml/substs@0.0.1@d41d8cd9"
      ],
      "devDependencies": [
        "ocaml@4.7.1004@d41d8cd9", "@opam/dune@opam:1.11.3@9894df55"
      ]
    },
    "@opam/menhir@opam:20190626@bbeb8953": {
      "id": "@opam/menhir@opam:20190626@bbeb8953",
      "name": "@opam/menhir",
      "version": "opam:20190626",
      "source": {
        "type": "install",
        "source": [
          "archive:https://opam.ocaml.org/cache/md5/78/783961f8d124449a1a335cc8e50f013f#md5:783961f8d124449a1a335cc8e50f013f",
          "archive:https://gitlab.inria.fr/fpottier/menhir/repository/20190626/archive.tar.gz#md5:783961f8d124449a1a335cc8e50f013f"
        ],
        "opam": {
          "name": "menhir",
          "version": "20190626",
          "path": "esy.lock/opam/menhir.20190626"
        }
      },
      "overrides": [],
      "dependencies": [
        "ocaml@4.7.1004@d41d8cd9", "@opam/ocamlfind@opam:1.8.1@c65fe06a",
        "@opam/ocamlbuild@opam:0.14.0@427a2331",
        "@esy-ocaml/substs@0.0.1@d41d8cd9"
      ],
      "devDependencies": [ "ocaml@4.7.1004@d41d8cd9" ]
    },
    "@opam/dune@opam:1.11.3@9894df55": {
      "id": "@opam/dune@opam:1.11.3@9894df55",
      "name": "@opam/dune",
      "version": "opam:1.11.3",
      "source": {
        "type": "install",
        "source": [
          "archive:https://opam.ocaml.org/cache/sha256/c8/c83a63e7e8245611b0e11d6adea07c6484dc1b4efffacb176315cd6674d4bbd2#sha256:c83a63e7e8245611b0e11d6adea07c6484dc1b4efffacb176315cd6674d4bbd2",
          "archive:https://github.com/ocaml/dune/releases/download/1.11.3/dune-build-info-1.11.3.tbz#sha256:c83a63e7e8245611b0e11d6adea07c6484dc1b4efffacb176315cd6674d4bbd2"
        ],
        "opam": {
          "name": "dune",
          "version": "1.11.3",
          "path": "esy.lock/opam/dune.1.11.3"
        }
      },
      "overrides": [
        {
          "opamoverride":
            "esy.lock/overrides/opam__s__dune_opam__c__1.11.3_opam_override"
        }
      ],
      "dependencies": [
        "ocaml@4.7.1004@d41d8cd9", "@opam/base-unix@opam:base@87d0b2eb",
        "@opam/base-threads@opam:base@36803084",
        "@esy-ocaml/substs@0.0.1@d41d8cd9"
      ],
      "devDependencies": [
        "ocaml@4.7.1004@d41d8cd9", "@opam/base-unix@opam:base@87d0b2eb",
        "@opam/base-threads@opam:base@36803084"
      ]
    },
    "@opam/cppo@opam:1.6.6@f4f83858": {
      "id": "@opam/cppo@opam:1.6.6@f4f83858",
      "name": "@opam/cppo",
      "version": "opam:1.6.6",
      "source": {
        "type": "install",
        "source": [
          "archive:https://opam.ocaml.org/cache/sha256/e7/e7272996a7789175b87bb998efd079794a8db6625aae990d73f7b4484a07b8a0#sha256:e7272996a7789175b87bb998efd079794a8db6625aae990d73f7b4484a07b8a0",
          "archive:https://github.com/ocaml-community/cppo/releases/download/v1.6.6/cppo-v1.6.6.tbz#sha256:e7272996a7789175b87bb998efd079794a8db6625aae990d73f7b4484a07b8a0"
        ],
        "opam": {
          "name": "cppo",
          "version": "1.6.6",
          "path": "esy.lock/opam/cppo.1.6.6"
        }
      },
      "overrides": [],
      "dependencies": [
        "ocaml@4.7.1004@d41d8cd9", "@opam/dune@opam:1.11.3@9894df55",
        "@opam/base-unix@opam:base@87d0b2eb",
        "@esy-ocaml/substs@0.0.1@d41d8cd9"
      ],
      "devDependencies": [
        "ocaml@4.7.1004@d41d8cd9", "@opam/dune@opam:1.11.3@9894df55",
        "@opam/base-unix@opam:base@87d0b2eb"
      ]
    },
    "@opam/conf-m4@opam:1@da6f4f44": {
      "id": "@opam/conf-m4@opam:1@da6f4f44",
      "name": "@opam/conf-m4",
      "version": "opam:1",
      "source": {
        "type": "install",
        "source": [ "no-source:" ],
        "opam": {
          "name": "conf-m4",
          "version": "1",
          "path": "esy.lock/opam/conf-m4.1"
        }
      },
      "overrides": [],
      "dependencies": [ "@esy-ocaml/substs@0.0.1@d41d8cd9" ],
      "devDependencies": []
    },
    "@opam/base-unix@opam:base@87d0b2eb": {
      "id": "@opam/base-unix@opam:base@87d0b2eb",
      "name": "@opam/base-unix",
      "version": "opam:base",
      "source": {
        "type": "install",
        "source": [ "no-source:" ],
        "opam": {
          "name": "base-unix",
          "version": "base",
          "path": "esy.lock/opam/base-unix.base"
        }
      },
      "overrides": [],
      "dependencies": [ "@esy-ocaml/substs@0.0.1@d41d8cd9" ],
      "devDependencies": []
    },
    "@opam/base-threads@opam:base@36803084": {
      "id": "@opam/base-threads@opam:base@36803084",
      "name": "@opam/base-threads",
      "version": "opam:base",
      "source": {
        "type": "install",
        "source": [ "no-source:" ],
        "opam": {
          "name": "base-threads",
          "version": "base",
          "path": "esy.lock/opam/base-threads.base"
        }
      },
      "overrides": [],
      "dependencies": [ "@esy-ocaml/substs@0.0.1@d41d8cd9" ],
      "devDependencies": []
    },
    "@opam/base@opam:v0.12.2@4eee02b5": {
      "id": "@opam/base@opam:v0.12.2@4eee02b5",
      "name": "@opam/base",
      "version": "opam:v0.12.2",
      "source": {
        "type": "install",
        "source": [
          "archive:https://opam.ocaml.org/cache/md5/71/7150e848a730369a2549d01645fb6c72#md5:7150e848a730369a2549d01645fb6c72",
          "archive:https://github.com/janestreet/base/archive/v0.12.2.tar.gz#md5:7150e848a730369a2549d01645fb6c72"
        ],
        "opam": {
          "name": "base",
          "version": "v0.12.2",
          "path": "esy.lock/opam/base.v0.12.2"
        }
      },
      "overrides": [],
      "dependencies": [
        "ocaml@4.7.1004@d41d8cd9", "@opam/sexplib0@opam:v0.12.0@e432406d",
        "@opam/dune@opam:1.11.3@9894df55", "@esy-ocaml/substs@0.0.1@d41d8cd9"
      ],
      "devDependencies": [
        "ocaml@4.7.1004@d41d8cd9", "@opam/sexplib0@opam:v0.12.0@e432406d",
        "@opam/dune@opam:1.11.3@9894df55"
      ]
    },
    "@esy-ocaml/substs@0.0.1@d41d8cd9": {
      "id": "@esy-ocaml/substs@0.0.1@d41d8cd9",
      "name": "@esy-ocaml/substs",
      "version": "0.0.1",
      "source": {
        "type": "install",
        "source": [
          "archive:https://registry.npmjs.org/@esy-ocaml/substs/-/substs-0.0.1.tgz#sha1:59ebdbbaedcda123fc7ed8fb2b302b7d819e9a46"
        ]
      },
      "overrides": [],
      "dependencies": [],
      "devDependencies": []
    },
    "@esy-ocaml/reason@3.5.0@d41d8cd9": {
      "id": "@esy-ocaml/reason@3.5.0@d41d8cd9",
      "name": "@esy-ocaml/reason",
      "version": "3.5.0",
      "source": {
        "type": "install",
        "source": [
          "archive:https://registry.npmjs.org/@esy-ocaml/reason/-/reason-3.5.0.tgz#sha1:f276b991ef0dfe4d559b68e554661f8b2bc618bf"
        ]
      },
      "overrides": [],
      "dependencies": [
        "ocaml@4.7.1004@d41d8cd9", "@opam/result@opam:1.4@6fb665c3",
        "@opam/ocamlfind@opam:1.8.1@c65fe06a",
        "@opam/ocaml-migrate-parsetree@opam:1.4.0@7f2e4334",
        "@opam/merlin-extend@opam:0.5@a5dd7d4b",
        "@opam/menhir@opam:20190626@bbeb8953",
        "@opam/dune@opam:1.11.3@9894df55"
      ],
      "devDependencies": []
    }
  }
}